arcade_outlook_mail/__init__.py
arcade_outlook_mail/_utils.py
arcade_outlook_mail/client.py
arcade_outlook_mail/constants.py
arcade_outlook_mail/enums.py
arcade_outlook_mail/message.py
arcade_outlook_mail/who_am_i_util.py
arcade_outlook_mail/tools/__init__.py
arcade_outlook_mail/tools/read.py
arcade_outlook_mail/tools/send.py
arcade_outlook_mail/tools/system_context.py
arcade_outlook_mail/tools/write.py
arcade_outlook_mail-2.3.0.dist-info/METADATA
arcade_outlook_mail-2.3.0.dist-info/WHEEL
arcade_outlook_mail-2.3.0.dist-info/licenses/LICENSE
arcade_outlook_mail-2.3.0.dist-info/RECORD
