Metadata-Version: 2.4
Name: arcade_outlook_mail
Version: 2.3.0
Summary: Arcade.dev LLM tools for Outlook Mail
Author-email: Arcade <dev@arcade.dev>
License: Proprietary - Arcade Software License Agreement v1.0
License-File: LICENSE
Requires-Python: >=3.10
Requires-Dist: arcade-tdk<4.0.0,>=3.0.0
Requires-Dist: beautifulsoup4<5.0.0,>=4.10.0
Requires-Dist: msgraph-sdk<2.0.0,>=1.28.0
Provides-Extra: dev
Requires-Dist: arcade-mcp[evals]<2.0.0,>=1.1.0; extra == 'dev'
Requires-Dist: arcade-serve<4.0.0,>=3.0.0; extra == 'dev'
Requires-Dist: mypy<2.0.0,>=1.5.1; extra == 'dev'
Requires-Dist: pre-commit<4.0.0,>=3.4.0; extra == 'dev'
Requires-Dist: pytest-asyncio<1.0.0,>=0.24.0; extra == 'dev'
Requires-Dist: pytest-cov<5.0.0,>=4.0.0; extra == 'dev'
Requires-Dist: pytest-mock<4.0.0,>=3.11.1; extra == 'dev'
Requires-Dist: pytest<9.0.0,>=8.3.0; extra == 'dev'
Requires-Dist: ruff<1.0.0,>=0.7.4; extra == 'dev'
Requires-Dist: tox<5.0.0,>=4.11.1; extra == 'dev'
